[
	{
	    "id": "battle_fury",
	    "name": "War Trance",
	    "cost": 30,
	    "effect": [ 1, 0, 0, 0 ],
	    "image": "spell06",
	    "persistent": true,
	    "stones": [],
	    "sound": "spell1035",
	    "target": "friendly",
	    "description": "War Trance permanently grants one friendly creature +1 Attack."
	},
	{
	    "id": "blind_ambition",
	    "name": "Reckless Oath",
	    "cost": 20,
	    "effect": [ 1, 1, 0, -2 ],
	    "image": "spell12",
	    "persistent": true,
	    "stones": [ "number6" ],
	    "target": "friendly",
	    "description": "Reckless Oath permanently grants one friendly creature +1 Attack and +1 Missile, but reduces its maximum Loyalty by 2."
	},
	{
	    "id": "brilliant_lights",
	    "name": "Radiant Burst",
	    "cost": 40,
	    "effect": [ 0, 0, -1, 0 ],
	    "image": "spell13",
	    "persistent": true,
	    "stones": [ "number7", "number9" ],
	    "target": "enemy",
	    "description": "Radiant Burst permanently reduces one enemy creature's Defense by 1."
	},
	{
	    "id": "demonic_compulsion",
	    "name": "Dark Command",
	    "cost": 30,
	    "effect": [ 0, 0, 0, 1 ],
	    "image": "spell02",
	    "persistent": true,
	    "stones": [],
	    "target": "friendly",
	    "description": "Dark Command permanently raises one friendly creature's maximum Loyalty by 1."
	},
	{
	    "id": "dispel_magic",
	    "name": "Unravel",
	    "cost": 120,
	    "effect": [],
	    "image": "spell16",
	    "stones": [],
	    "sound": "spell1032",
	    "target": "any",
	    "description": "Unravel removes every spell enchantment from one creature, friendly or enemy. Innate special abilities remain."
	},
	{
	    "id": "dust_cloud",
	    "name": "Blinding Dust",
	    "cost": 30,
	    "effect": [ -1, 0, 0, 0 ],
	    "image": "spell09",
	    "persistent": true,
	    "stones": [ "sword5", "sword8" ],
	    "target": "enemy",
	    "description": "Blinding Dust permanently reduces one enemy creature's Attack by 1."
	},
	{
	    "id": "force_shield",
	    "name": "Aegis",
	    "cost": 30,
	    "effect": [ 0, 0, 0, 0 ],
	    "value": 1,
	    "image": "spell08",
	    "persistent": true,
	    "stones": [ "sword7", "sword9" ],
	    "target": "friendly",
	    "description": "Aegis permanently reduces missile and territory-fire damage against one friendly creature by 1."
	},
	{
	    "id": "guidance",
	    "name": "Guiding Star",
	    "cost": 20,
	    "effect": [ 0, 1, 0, 0 ],
	    "image": "spell07",
	    "persistent": true,
	    "stones": [ "sword6" ],
	    "sound": "spell1035",
	    "target": "friendly",
	    "description": "Guiding Star permanently grants one friendly creature +1 Missile."
	},
	{
	    "id": "healing",
	    "name": "Mend",
	    "cost": 100,
	    "effect": [ 0, 0, 0, 2 ],
	    "image": "spell18",
	    "sound": "spell1031",
	    "stones": [],
	    "target": "friendly",
	    "description": "Mend restores 2 current Loyalty to one friendly creature, never above its maximum."
	},
	{
	    "id": "hell_blast",
	    "name": "Inferno",
	    "cost": 80,
	    "effect": [ 0, 0, 0, -2 ],
	    "image": "spell19",
	    "sound": "spell1023",
	    "stones": [ "skull6", "dragon3" ],
	    "target": "enemy_party",
	    "description": "Inferno immediately deals 2 Loyalty damage to every creature in one enemy company."
	},
	{
	    "id": "heroism",
	    "name": "Valiant Heart",
	    "cost": 30,
	    "effect": [ 1, 0, 0, 1 ],
	    "image": "spell10",
	    "persistent": true,
	    "stones": [ "sword4", "sword9" ],
	    "sound": "spell1035",
	    "target": "friendly",
	    "description": "Valiant Heart permanently grants one friendly creature +1 Attack and +1 maximum Loyalty."
	},
	{
	    "id": "lightning_bolt",
	    "name": "Storm Lance",
	    "cost": 80,
	    "effect": [ 0, 0, 0, -1 ],
	    "image": "spell17",
	    "sound": "spell1030",
	    "stones": [],
	    "target": "enemy",
	    "description": "Storm Lance immediately deals 1 Loyalty damage to one enemy creature."
	},
	{
	    "id": "magical_aura",
	    "name": "Arcane Mantle",
	    "cost": 40,
	    "effect": [ 0, 0, 1, 0 ],
	    "image": "spell14",
	    "persistent": true,
	    "stones": [ "skull2", "skull5" ],
	    "target": "friendly",
	    "description": "Arcane Mantle permanently grants one friendly creature +1 Defense."
	},
	{
	    "id": "mass_dispel",
	    "name": "Great Unraveling",
	    "cost": 120,
	    "effect": [],
	    "image": "spell16",
	    "stones": [],
	    "sound": "spell1032",
	    "target": "land",
	    "description": "Great Unraveling removes every spell enchantment from all creatures in the selected land. Innate special abilities remain."
	},
	{
	    "id": "mass_panic",
	    "name": "Dread Wave",
	    "cost": 50,
	    "effect": [ 0, 0, 0, -1 ],
	    "image": "spell03",
	    "persistent": true,
	    "stones": [ "skull7", "skull9" ],
	    "target": "enemy_party",
	    "description": "Dread Wave permanently reduces the maximum Loyalty of every creature in one enemy company by 1."
	},
	{
	    "id": "mystical_fountain",
	    "name": "Wellspring",
	    "cost": 30,
	    "effect": [ 1, 1, 0, 1 ],
	    "image": "spell11",
	    "persistent": true,
	    "stones": [],
	    "sound": "spell1033",
	    "target": "friendly",
	    "description": "Wellspring permanently grants one friendly creature a random +1 bonus to Attack, Missile or maximum Loyalty."
	},
	{
	    "id": "mystical_fountain_attack",
	    "name": "Wellspring of Might",
	    "cost": 30,
	    "effect": [ 1, 0, 0, 0 ],
	    "image": "spell11",
	    "persistent": true,
	    "stones": [],
	    "sound": "spell1033",
	    "target": "friendly",
	    "description": "Wellspring of Might is the Attack outcome of Wellspring and permanently grants +1 Attack."
	},
	{
	    "id": "mystical_fountain_range",
	    "name": "Wellspring of Reach",
	    "cost": 30,
	    "effect": [ 0, 1, 0, 0 ],
	    "image": "spell11",
	    "persistent": true,
	    "stones": [],
	    "sound": "spell1033",
	    "target": "friendly",
	    "description": "Wellspring of Reach is the Missile outcome of Wellspring and permanently grants +1 Missile."
	},
	{
	    "id": "mystical_fountain_loyalty",
	    "name": "Wellspring of Vigor",
	    "cost": 30,
	    "effect": [ 0, 0, 0, 1 ],
	    "image": "spell11",
	    "persistent": true,
	    "stones": [],
	    "sound": "spell1033",
	    "target": "friendly",
	    "description": "Wellspring of Vigor is the Loyalty outcome of Wellspring and permanently grants +1 maximum Loyalty."
	},
	{
	    "id": "paralyze",
	    "name": "Binding Sigil",
	    "cost": 40,
	    "effect": [],
	    "duration": 1,
	    "image": "spell04",
	    "persistent": true,
	    "stones": [ "skull5", "skull8" ],
	    "sound": "spell1034",
	    "target": "enemy",
	    "description": "Binding Sigil prevents one enemy creature from acting for one battle turn."
	},
	{
	    "id": "reduction",
	    "name": "Withering Mark",
	    "cost": 60,
	    "effect": [ -1, 0, -1, 0 ],
	    "image": "spell05",
	    "persistent": true,
	    "stones": [ "skull4", "skull9" ],
	    "target": "enemy",
	    "description": "Withering Mark permanently reduces one enemy creature's Attack and Defense by 1."
	},
	{
	    "id": "smoke",
	    "name": "Veil of Smoke",
	    "cost": 20,
	    "effect": [ 0, -1, 0, 0 ],
	    "image": "spell01",
	    "persistent": true,
	    "stones": [ "number8" ],
	    "target": "enemy",
	    "description": "Veil of Smoke permanently reduces one enemy creature's Missile by 1, to a minimum effective value of zero."
	},
	{
	    "id": "teleport",
	    "name": "Waystep",
	    "cost": 50,
	    "image": "spell15",
	    "stones": [ "number4", "number9" ],
	    "target": "friendly",
	    "description": "Waystep moves one friendly creature directly to any friendly land."
	},
	{
	    "id": "mana_fog",
	    "name": "Essence Haze",
	    "cost": 30,
	    "duration": 3,
	    "stones": [ "wind3" ],
	    "target": "all_players",
	    "description": "Essence Haze affects every wizard and prevents ordinary spell casting and creature summoning for 3 turns."
	},
	{
	    "id": "random_discard",
	    "name": "Shatter Rune",
	    "cost": 30,
	    "duration": 1,
	    "stones": [ "wind2" ],
	    "sound": "spell1036",
	    "target": "other_player",
	    "description": "Shatter Rune forces one rival wizard to discard a random rune during their next turn."
	},
	{
	    "id": "scry_runes",
	    "name": "Rune Sight",
	    "cost": 30,
	    "duration": 5,
	    "stones": [ "wind1" ],
	    "sound": "spell1036",
	    "target": "other_player",
	    "description": "Rune Sight reveals one rival's concealed hand to the caster for 5 turns."
	},
	{
	    "id": "silence",
	    "name": "Hush",
	    "cost": 30,
	    "duration": 3,
	    "stones": [ "wind4" ],
	    "sound": "spell1036",
	    "target": "other_player",
	    "description": "Hush prevents one rival from calling Chao, Pung, Kong or Game and from casting or summoning for 3 turns. Telepaths are immune."
	},
	{
	    "id": "draw_number",
	    "name": "Call Number Rune",
	    "cost": 40,
	    "duration": 1,
	    "stones": [],
	    "sound": "spell1035",
	    "target": "my_player",
	    "description": "Call Number Rune directs your next draw to a Number rune if one remains in the wall."
	},
	{
	    "id": "draw_skull",
	    "name": "Call Bone Rune",
	    "cost": 40,
	    "duration": 1,
	    "stones": [],
	    "sound": "spell1035",
	    "target": "my_player",
	    "description": "Call Bone Rune directs your next draw to a Bone rune if one remains in the wall."
	},
	{
	    "id": "draw_sword",
	    "name": "Call Blade Rune",
	    "cost": 40,
	    "duration": 1,
	    "stones": [],
	    "sound": "spell1035",
	    "target": "my_player",
	    "description": "Call Blade Rune directs your next draw to a Blade rune if one remains in the wall."
	}
]
